CITATION
LICENSE
MANIFEST.in
README.rst
requirements.txt
setup.py
pmipy/BIT.py
pmipy/OCMFeatureExtract.py
pmipy/OCMVisualization.py
pmipy/UploadDatabase.py
pmipy/__init__.py
pmipy/command_line.py
pmipy/demand_predict.py
pmipy/featureEngineer.py
pmipy/featureEngineer2.py
pmipy/getHyperMarket2.py
pmipy/getOcmData.py
pmipy/getPeopleFlow.py
pmipy/getTargetCoordinate.py
pmipy/log.py
pmipy/pmi.py
pmipy/untitled0.py
pmipy/updateTileData.py
pmipy/updateTileData2.py
pmipy/xlwings.applescript
pmipy.egg-info/PKG-INFO
pmipy.egg-info/SOURCES.txt
pmipy.egg-info/dependency_links.txt
pmipy.egg-info/entry_points.txt
pmipy.egg-info/requires.txt
pmipy.egg-info/top_level.txt
pmipy/BITauto/BIT_sheet2.py
pmipy/BITauto/BIT_sheet3.py
pmipy/BITauto/BIT_sheet4_new.py
pmipy/BITauto/BIT_sheet5.py
pmipy/BITauto/BIT_sheet6.py
pmipy/BITauto/BIT_sheet7.py
pmipy/BITauto/__init__.py
pmipy/DemandPredict/AnalyzeGrading.py
pmipy/DemandPredict/Visualization.py
pmipy/DemandPredict/__init__.py
pmipy/DemandPredict/adjustment_interpreter.py
pmipy/DemandPredict/calShipment.py
pmipy/DemandPredict/grading.py
pmipy/DemandPredict/machineLearning.py
pmipy/DemandPredict/main.py
pmipy/DemandPredict/python正负因子.py
pmipy/DemandPredict/updateFactor.py
pmipy/DemandPredict/volumeEstimate.py
pmipy/DemandPredict/商圈mapping及取数.py
pmipy/DemandPredict/商圈调整策略.py
pmipy/DemandPredict/因子和通路数据更新.py
pmipy/DemandPredict/地理特征聚类.py
pmipy/DemandPredict/康师傅出货量计算.py
pmipy/DemandPredict/总市场量推估2.py
pmipy/DemandPredict/机器学习训练.py
pmipy/OCM/__init__.py
pmipy/OCM/getFactor.py
pmipy/OCM/getRegionFactor.py
pmipy/OCM/getTileFactor.py
pmipy/OCM/getTileName.py
pmipy/OCM/updateRegionFactor.py
pmipy/OCM/updateTileFactor.py
pmipy/Rscript/OCM_feature.r
pmipy/support/APIkeys.py
pmipy/support/__init__.py
pmipy/support/prov_mapp.py
pmipy/tests/__init__.py
pmipy/tests/common.py
pmipy/tests/sample_picture.png
tips/Anaconda右键注册表修改.reg