Metadata-Version: 1.1
Name: pmipy
Version: 0.13.4
Summary: A tool for my team.
Home-page: UNKNOWN
Author: biojim
Author-email: biojxz@163.com
License: MIT
Keywords: I don't want to tell you!
Platform: Windows
Classifier: License :: OSI Approved :: MIT License
Classifier: Programming Language :: Python
Classifier: Programming Language :: Python :: 2.7
Classifier: Programming Language :: Python :: 3
Classifier: Topic :: Office/Business :: Financial :: Spreadsheet
Classifier: License :: OSI Approved :: BSD License
